fam_analytics_py/__init__.py
fam_analytics_py/base/__init__.py
fam_analytics_py/base/client.py
fam_analytics_py/base/consumer.py
fam_analytics_py/clevertap/__init__.py
fam_analytics_py/clevertap/client.py
fam_analytics_py/clevertap/config.py
fam_analytics_py/clevertap/consumer.py
fam_analytics_py/exceptions.py
fam_analytics_py/globals.py
fam_analytics_py/mixpanel/__init__.py
fam_analytics_py/mixpanel/client.py
fam_analytics_py/mixpanel/config.py
fam_analytics_py/mixpanel/constants.py
fam_analytics_py/mixpanel/consumer.py
fam_analytics_py/request.py
fam_analytics_py/segment/__init__.py
fam_analytics_py/segment/client.py
fam_analytics_py/segment/config.py
fam_analytics_py/segment/consumer.py
fam_analytics_py/types.py
fam_analytics_py/utils.py
fam_analytics_py-1.0.0.dist-info/METADATA
fam_analytics_py-1.0.0.dist-info/WHEEL
fam_analytics_py-1.0.0.dist-info/RECORD
