Metadata-Version: 2.1
Name: fam-analytics-py
Version: 1.0.0
Summary: Analytics module for Python projects
Author: galaxyzpjfp
Author-email: pranav.jain@fampay.in
Requires-Python: >=3.8.1,<4.0.0
Classifier: Programming Language :: Python :: 3
Classifier: Programming Language :: Python :: 3.9
Classifier: Programming Language :: Python :: 3.10
Classifier: Programming Language :: Python :: 3.11
Classifier: Programming Language :: Python :: 3.12
Requires-Dist: python-dateutil (>=2.8.2,<3.0.0)
Requires-Dist: requests (>=2.28.1,<3.0.0)
Requires-Dist: six (>=1.16.0,<2.0.0)
